quenv/__init__.py
quenv/admin.py
quenv/apps.py
quenv/licenses.py
quenv/managers.py
quenv/models.py
quenv/tests.py
quenv/management/__init__.py
quenv/management/commands/__init__.py
quenv/management/commands/quenv.py
quenv/migrations/0001_initial.py
quenv/migrations/0002_auto_20200731_1947.py
quenv/migrations/0003_auto_20200801_1912.py
quenv/migrations/__init__.py
django_quenv-0.1.6.dist-info/LICENSE
django_quenv-0.1.6.dist-info/METADATA
django_quenv-0.1.6.dist-info/WHEEL
django_quenv-0.1.6.dist-info/top_level.txt
django_quenv-0.1.6.dist-info/RECORD
