Metadata-Version: 2.1
Name: django-quenv
Version: 0.1.6
Summary: A django application that gathers the names of all installed packages in a virtualenv, their licenses along with related quality metrics, in django-admin.
Home-page: https://github.com/raratiru/django-quenv
Author: George Tantiras
License: BSD 3-Clause License
Platform: UNKNOWN
Classifier: Development Status :: 3 - Alpha
Classifier: Environment :: Web Environment
Classifier: Framework :: Django
Classifier: Intended Audience :: Developers
Classifier: License :: OSI Approved :: BSD License
Classifier: Operating System :: OS Independent
Classifier: Programming Language :: Python
Classifier: Programming Language :: Python :: 3 :: Only
Classifier: Programming Language :: Python :: 3.5
Classifier: Programming Language :: Python :: 3.6
Classifier: Programming Language :: Python :: 3.7
Classifier: Programming Language :: Python :: 3.8
Classifier: Natural Language :: English
Classifier: Topic :: Internet :: WWW/HTTP
Classifier: Topic :: Internet :: WWW/HTTP :: Dynamic Content
Classifier: Topic :: Internet :: WWW/HTTP :: Site Management
Requires-Python: >=3.5
Requires-Dist: setuptools
Requires-Dist: tqdm
Requires-Dist: Django
Requires-Dist: requests
